README.rst
setup.py
deephlapan/__init__.py
deephlapan/deephlapan.py
deephlapan.egg-info/PKG-INFO
deephlapan.egg-info/SOURCES.txt
deephlapan.egg-info/dependency_links.txt
deephlapan.egg-info/requires.txt
deephlapan.egg-info/top_level.txt