Metadata-Version: 1.0
Name: deephlapan
Version: 0.1
Summary: Used for predicting the binding level between peptides and HLA alleles
Home-page: https://github.com/
Author: Jingcheng Wu
Author-email: 21619014@zju.edu.cn
License: GNU
Platform: UNKNOWN
